cupdlpx/__init__.py
cupdlpx/_core.py
cupdlpx/_cupdlpx_core.cp312-win_amd64.pyd
cupdlpx/model.py
cupdlpx/PDLP.py
cupdlpx-0.1.2.dist-info/METADATA
cupdlpx-0.1.2.dist-info/WHEEL
cupdlpx-0.1.2.dist-info/licenses/LICENSE
cupdlpx-0.1.2.dist-info/RECORD
