Metadata-Version: 2.2
Name: cupdlpx
Version: 0.1.2
Summary: Python bindings for cuPDLPx (GPU-accelerated first-order LP solver)
Author: Haihao Lu, Zedong Peng, Jinwen Yang, Bo Tang
License: Apache-2.0
Requires-Python: >=3.8
Requires-Dist: numpy>=1.21
Requires-Dist: scipy>=1.8
Provides-Extra: test
Requires-Dist: pytest>=8; extra == "test"
Requires-Dist: pytest-cov>=4; extra == "test"
Requires-Dist: numpy; extra == "test"
Requires-Dist: scipy; extra == "test"
